spalah/__init__.py
spalah/dataframe/__init__.py
spalah/dataframe/dataframe.py
spalah/dataset/DeltaTableConfig.py
spalah/dataset/__init__.py
spalah/shared/__init__.py
spalah/shared/logging.py
spalah-1.1.9.dist-info/licenses/LICENSE
spalah-1.1.9.dist-info/METADATA
spalah-1.1.9.dist-info/WHEEL
spalah-1.1.9.dist-info/top_level.txt
spalah-1.1.9.dist-info/RECORD
