Metadata-Version: 2.4
Name: spalah
Version: 1.1.9
Summary: Spalah is a set of PySpark dataframe helpers
Author-email: Alex Volok <alexandr.volok@gmail.com>
License-Expression: MIT
Keywords: spalah
Classifier: Intended Audience :: Developers
Classifier: Natural Language :: English
Classifier: Programming Language :: Python :: 3
Classifier: Programming Language :: Python :: 3.11
Classifier: Programming Language :: Python :: 3.12
Requires-Python: <4.0.0,>=3.11.0
License-File: LICENSE
Provides-Extra: build
Requires-Dist: uv~=0.9.25; extra == "build"
Dynamic: license-file
